what_the_diff/__init__.py
what_the_diff/formatters.py
what_the_diff/utils.py
what_the_diff-0.1.dist-info/METADATA
what_the_diff-0.1.dist-info/WHEEL
what_the_diff-0.1.dist-info/top_level.txt
what_the_diff-0.1.dist-info/RECORD
