Metadata-Version: 2.1
Name: what-the-diff
Version: 0.1
Summary: Unix diff implementation in python
Home-page: http://github.com/hskang9/what_the_diff
Author: Hyungsuk Kang
Author-email: hskang9@gmail.com
License: MIT
Platform: UNKNOWN
Requires-Dist: termcolor
Requires-Dist: nltk
